bg_reports_sdk/__init__.py
bg_reports_sdk/config.py
bg_reports_sdk/data_provider/__init__.py
bg_reports_sdk/data_provider/data_provider.py
bg_reports_sdk/report_executor/__init__.py
bg_reports_sdk/report_executor/report_executor.py
bg_reports_sdk/scheduler_manager/__init__.py
bg_reports_sdk/scheduler_manager/scheduler.py
bg_reports_sdk/scheduler_manager/scheduler_manager.py
bg_reports_sdk-1.0.2.dist-info/METADATA
bg_reports_sdk-1.0.2.dist-info/WHEEL
bg_reports_sdk-1.0.2.dist-info/top_level.txt
bg_reports_sdk-1.0.2.dist-info/RECORD
